{"id":"120363185673594577@g.us","subject":"[ • Mundo Místico • ]","subjectOwner":"5511987702941@s.whatsapp.net","subjectTime":1702060348,"size":1,"creation":1702060348,"owner":"5511987702941@s.whatsapp.net","desc":"Olá! Criamos a comunidade no intuito de criarmos vários grupos, tanto de jogos, futebol, esportes, nsfw e etc.. Espero que se divirta na comunidade!!\n\nPara criar um grupo apenas consulte eu ou o capi\n\nAdms: Soares (eu), Capi","descId":"AC79C4D2F5DF95173EBBC21070582319","restrict":false,"announce":false,"isCommunity":true,"isCommunityAnnounce":false,"joinApprovalMode":false,"memberAddMode":false,"participants":[{"id":"5511987702941@s.whatsapp.net","admin":"superadmin"}],"time":1749310620}